otp2289/__init__.py
otp2289/__main__.py
otp2289/generator.py
otp2289/server.py
pyotp2289-1.2.1.dist-info/COPYING
pyotp2289-1.2.1.dist-info/LICENSE
pyotp2289-1.2.1.dist-info/METADATA
pyotp2289-1.2.1.dist-info/WHEEL
pyotp2289-1.2.1.dist-info/entry_points.txt
pyotp2289-1.2.1.dist-info/top_level.txt
pyotp2289-1.2.1.dist-info/RECORD
