Metadata-Version: 2.1
Name: pyotp2289
Version: 1.2.1
Summary: A pure Python implementation of "A One-Time Password System"
Home-page: https://github.com/blackm0re/pyotp2289
Author: attr: otp2289.__author__
Author-email: sgs@pichove.org
Project-URL: Bug Tracker, https://github.com/blackm0re/pyotp2289/issues
Project-URL: Source, https://github.com/blackm0re/pyotp2289
Project-URL: API Documentation, https://gnulover.simeonov.no/docs/api/pyotp2289/latest/
Classifier: Development Status :: 5 - Production/Stable
Classifier: Intended Audience :: Developers
Classifier: License :: OSI Approved :: BSD License
Classifier: Programming Language :: Python :: 3
Classifier: Programming Language :: Python :: 3.7
Classifier: Programming Language :: Python :: 3.8
Classifier: Programming Language :: Python :: 3.9
Classifier: Programming Language :: Python :: 3.10
Classifier: Programming Language :: Python :: 3.11
Classifier: Programming Language :: Python :: 3.12
Classifier: Programming Language :: Python :: Implementation
Classifier: Operating System :: OS Independent
Classifier: Topic :: Security :: Cryptography
Requires-Python: >=3.7
License-File: LICENSE
License-File: COPYING
